setup.cfg
setup.py
py3_cli/__init__.py
py3_cli/case.py
py3_cli/cmd.py
py3_cli/error.py
py3_cli/flag.py
py3_cli/handler.py
py3_cli/main.py
py3_cli.egg-info/PKG-INFO
py3_cli.egg-info/SOURCES.txt
py3_cli.egg-info/dependency_links.txt
py3_cli.egg-info/requires.txt
py3_cli.egg-info/top_level.txt