Metadata-Version: 1.0
Name: py3-cli
Version: 0.1.2
Summary: py3-cli - a simple python framework for creating CLI, implemented by calling functions using commands.
Home-page: UNKNOWN
Author: JkLEnot
Author-email: jklenot123@gmail.com
License: UNKNOWN
Platform: UNKNOWN
